tabdeal/__init__.py
tabdeal/__version__.py
tabdeal/client.py
tabdeal/enums.py
tabdeal/exceptions.py
tabdeal/isolated_margin.py
tabdeal/spot.py
tabdeal/utils.py
tabdeal/websocket_client.py
tabdeal_python-0.4.7.data/data/base.txt
tabdeal_python-0.4.7.dist-info/METADATA
tabdeal_python-0.4.7.dist-info/WHEEL
tabdeal_python-0.4.7.dist-info/top_level.txt
tabdeal_python-0.4.7.dist-info/RECORD
