Metadata-Version: 2.4
Name: tabdeal-python
Version: 0.4.7
Summary: Official python package to use Tabdeal API
Home-page: https://github.com/Tabdeal-Exchange/tabdeal-python
Author: Amin Basiri
Author-email: amin.bsr99@gmail.com
Project-URL: Bug Tracker, https://github.com/Tabdeal-Exchange/tabdeal-python/issues
Classifier: Programming Language :: Python :: 3
Classifier: Operating System :: OS Independent
Requires-Python: >=3.6
Requires-Dist: requests==2.27.1
Requires-Dist: websocket-client==1.3.3
Dynamic: author
Dynamic: author-email
Dynamic: classifier
Dynamic: description
Dynamic: description-content-type
Dynamic: home-page
Dynamic: project-url
Dynamic: requires-dist
Dynamic: requires-python
Dynamic: summary
